adi_ad9082_v170.cpython-310-x86_64-linux-gnu.so
adi_ad9082_v170/LICENSES.pdf
adi_ad9082_v170/__init__.pyi
adi_ad9082_v170/py.typed
quel_ic_config/__init__.py
quel_ic_config/abstract_ic.py
quel_ic_config/ad5328.py
quel_ic_config/ad7490.py
quel_ic_config/ad9082.py
quel_ic_config/ad9082_nco.py
quel_ic_config/adrf6780.py
quel_ic_config/box_force_unlock.py
quel_ic_config/box_lock.py
quel_ic_config/e7resource_mapper.py
quel_ic_config/exstickge_coap_client.py
quel_ic_config/exstickge_coap_tempctrl_client.py
quel_ic_config/exstickge_proxy.py
quel_ic_config/exstickge_sock_client.py
quel_ic_config/linkupper.py
quel_ic_config/lmx2594.py
quel_ic_config/mixerboard_gpio.py
quel_ic_config/pathselectorboard_gpio.py
quel_ic_config/powerboard_pwm.py
quel_ic_config/py.typed
quel_ic_config/quel1_any_config_subsystem.py
quel_ic_config/quel1_box.py
quel_ic_config/quel1_box_intrinsic.py
quel_ic_config/quel1_config_loader.py
quel_ic_config/quel1_config_subsystem.py
quel_ic_config/quel1_config_subsystem_common.py
quel_ic_config/quel1_config_subsystem_tempctrl.py
quel_ic_config/quel1_thermistor.py
quel_ic_config/quel1_wave_subsystem.py
quel_ic_config/quel1se_adda_config_subsystem.py
quel_ic_config/quel1se_config_subsystem.py
quel_ic_config/quel1se_fujitsu11_config_subsystem.py
quel_ic_config/quel1se_riken8_config_subsystem.py
quel_ic_config/quel_clock_master_v1.py
quel_ic_config/quel_config_common.py
quel_ic_config/quel_ic.py
quel_ic_config/rfswitcharray.py
quel_ic_config/settings/quel-1.json
quel_ic_config/settings/quel-1se-adda.json
quel_ic_config/settings/quel-1se-fujitsu11.json
quel_ic_config/settings/quel-1se-riken8.json
quel_ic_config/settings/quel-2-proto-adda.json
quel_ic_config/settings/quel-1/ad5328.json
quel_ic_config/settings/quel-1/ad9082.json
quel_ic_config/settings/quel-1/ad9082_cduc1500mhz_dacclk12000mhz.json
quel_ic_config/settings/quel-1/ad9082_cduc2000mhz_dacclk12000mhz.json
quel_ic_config-0.10.7.dist-info/METADATA
quel_ic_config-0.10.7.dist-info/WHEEL
quel_ic_config-0.10.7.dist-info/entry_points.txt
quel_ic_config-0.10.7.dist-info/top_level.txt
quel_ic_config-0.10.7.dist-info/RECORD
quel_ic_config-0.10.7.dist-info/licenses/LICENSE
quel_ic_config-0.10.7.dist-info/licenses/NOTICE
