Metadata-Version: 2.4
Name: quel_ic_config
Version: 0.10.7
Summary: A host-side software intended for QuEL control devices
Author-email: quelware Authors <opensource@quel-inc.com>
License:                                  Apache License
Project-URL: Repository, https://github.com/quel-inc/quelware
Classifier: Programming Language :: Python :: 3
Classifier: Operating System :: OS Independent
Requires-Python: >=3.9
License-File: LICENSE
License-File: NOTICE
Requires-Dist: packaging>=23.2
Requires-Dist: numpy~=1.26.0
Requires-Dist: pydantic~=2.4
Requires-Dist: pyyaml~=6.0.1
Requires-Dist: aiocoap>=0.4.7
Requires-Dist: python-ulid~=2.7.0
Requires-Dist: flufl.lock~=8.1.0
Requires-Dist: e7awghal>0.1.3
Requires-Dist: pybind11-stubgen~=2.5.1
Requires-Dist: pandas~=2.2.3
Requires-Dist: polars~=1.9.0
Requires-Dist: matplotlib
Requires-Dist: typer>=0.16.1
Provides-Extra: dev
Requires-Dist: black; extra == "dev"
Requires-Dist: mypy; extra == "dev"
Requires-Dist: types-PyYAML; extra == "dev"
Requires-Dist: pytest; extra == "dev"
Requires-Dist: pytest-cov; extra == "dev"
Requires-Dist: pybind11~=2.13.6; extra == "dev"
Requires-Dist: pandas-stubs; extra == "dev"
Requires-Dist: quel_cmod_scripting>=0.1.8; extra == "dev"
Requires-Dist: quel_staging_tool>=0.0.8; extra == "dev"
Requires-Dist: quel_pyxsdb>=0.2.0; extra == "dev"
Requires-Dist: ruff>=0.11.13; extra == "dev"
Dynamic: license-file
